sumry/__init__.py
sumry/cli.py
sumry/main.py
sumry/readers.py
sumry/timing.py
sumry/formats/__init__.py
sumry/formats/base.py
sumry/formats/xlsx.py
sumry-0.4.0.dist-info/licenses/LICENSE
sumry-0.4.0.dist-info/METADATA
sumry-0.4.0.dist-info/WHEEL
sumry-0.4.0.dist-info/entry_points.txt
sumry-0.4.0.dist-info/top_level.txt
sumry-0.4.0.dist-info/RECORD
