Metadata-Version: 2.4
Name: sumry
Version: 0.4.0
Summary: A data summarization tool for analyzing various file formats
Author: Sparkgeo
License: MIT
Project-URL: Homepage, https://github.com/sparkgeo/sumry
Project-URL: Repository, https://github.com/sparkgeo/sumry
Project-URL: Issues, https://github.com/sparkgeo/sumry/issues
Keywords: data,summary,analysis,cli
Classifier: Development Status :: 3 - Alpha
Classifier: Intended Audience :: Developers
Classifier: License :: OSI Approved :: MIT License
Classifier: Programming Language :: Python :: 3
Classifier: Programming Language :: Python :: 3.12
Classifier: Topic :: Software Development :: Libraries :: Python Modules
Requires-Python: >=3.12
License-File: LICENSE
Requires-Dist: duckdb>=1.1.2
Requires-Dist: geopandas>=1.0.1
Requires-Dist: openpyxl>=3.1.5
Requires-Dist: pyarrow>=17.0.0
Requires-Dist: python-calamine>=0.2.3
Requires-Dist: rasterio>=1.3.0
Requires-Dist: rich>=13.0.0
Requires-Dist: typer>=0.12.5
Dynamic: license-file
